{
    "name":"cbi18n-json-resources",
    "version":"0.3.0",
    "author":"Wil de Bruin",
    "location":"https://github.com/wpdebruin/cbi18n-json-resources/archive/main.zip",
    "homepage":"shiftinsert.nl",
    "documentation":"",
    "repository":{
        "type":"",
        "URL":""
    },
    "bugs":"",
    "slug":"cbi18n-json-resources",
    "shortDescription":"A sweet package",
    "description":"",
    "instructions":"",
    "changelog":"",
    "type":"modules",
    "keywords":"cbi18n json language internationalization",
    "private":false,
    "projectURL":"",
    "license":[
        {
            "type":"",
            "URL":""
        }
    ],
    "contributors":[],
    "dependencies":{},
    "devDependencies":{},
    "installPaths":{},
    "scripts":{},
    "ignore":[
        "**/.*",
        "/test/",
        "/tests/"
    ],
    "testbox":{
        "bundles":"",
        "directory":"tests.specs",
        "excludes":"",
        "labels":"",
        "options":{},
        "recurse":true,
        "reporter":"",
        "runner":[
            {
                "default":""
            }
        ],
        "testBundles":"",
        "testSpecs":"",
        "testSuites":"",
        "verbose":true,
        "watchDelay":500,
        "watchPaths":"**.cfc"
    }
}
